{
  "constraints": {
    "max_gate_count": {},
    "optimization_parameter": "no_opt"
  },
  "preferences": {
    "machine_precision": 8,
    "custom_hardware_settings": {
      "basis_gates": [
        "ry",
        "r",
        "t",
        "x",
        "z",
        "u2",
        "p",
        "rz",
        "cz",
        "h",
        "u1",
        "sx",
        "rx",
        "y",
        "tdg",
        "sdg",
        "s",
        "sxdg",
        "u",
        "id",
        "cy",
        "cx"
      ],
      "is_symmetric_connectivity": true
    },
    "debug_mode": true,
    "synthesize_all_separately": false,
    "optimization_level": 3,
    "output_format": [
      "qasm"
    ],
    "pretty_qasm": true,
    "transpilation_option": "auto optimize",
    "timeout_seconds": 300,
    "random_seed": 2302908612
  }
}