{
  "constraints": {
    "max_gate_count": {},
    "optimization_parameter": "no_opt"
  },
  "preferences": {
    "custom_hardware_settings": {
      "basis_gates": [
        "s",
        "ry",
        "u1",
        "tdg",
        "rx",
        "u",
        "y",
        "sxdg",
        "cz",
        "sdg",
        "h",
        "x",
        "rz",
        "cx",
        "cy",
        "id",
        "u2",
        "r",
        "p",
        "sx",
        "t",
        "z"
      ],
      "is_symmetric_connectivity": true
    },
    "debug_mode": true,
    "machine_precision": 8,
    "optimization_level": 0,
    "output_format": ["qasm"],
    "pretty_qasm": true,
    "random_seed": 3307564258,
    "synthesize_all_separately": false,
    "timeout_seconds": 300,
    "transpilation_option": "auto optimize"
  }
}
